chromadol/__init__.py
chromadol/base.py
chromadol/data_loaders.py
chromadol/util.py
chromadol/tests/__init__.py
chromadol/tests/base_test.py
chromadol-0.1.2.dist-info/LICENSE
chromadol-0.1.2.dist-info/METADATA
chromadol-0.1.2.dist-info/WHEEL
chromadol-0.1.2.dist-info/top_level.txt
chromadol-0.1.2.dist-info/RECORD
