Metadata-Version: 2.1
Name: chromadol
Version: 0.1.2
Summary: Data Object Layer for ChromaDB
Author: OtoSense
License: mit
License-File: LICENSE
Requires-Dist: dol
Requires-Dist: chromadb
